slots/__init__.py
slots/slots.py
slots-0.4.0.dist-info/LICENSE.txt
slots-0.4.0.dist-info/METADATA
slots-0.4.0.dist-info/WHEEL
slots-0.4.0.dist-info/top_level.txt
slots-0.4.0.dist-info/RECORD
