Metadata-Version: 2.1
Name: slots
Version: 0.4.0
Summary: A multi-armed bandit library for Python
Home-page: https://github.com/roycoding/slots
Author: Roy Keyes
Author-email: roy.coding@gmail.com
License: MIT
Keywords: multi-armed bandit hypothesis testing
Platform: UNKNOWN
Classifier: Development Status :: 3 - Alpha
Classifier: Intended Audience :: Developers
Classifier: Intended Audience :: Science/Research
Classifier: Topic :: Scientific/Engineering
Classifier: License :: OSI Approved :: MIT License
Classifier: Programming Language :: Python :: 3.5
Classifier: Programming Language :: Python :: 3.6
Classifier: Programming Language :: Python :: 3.7
